azure/mgmt/pineconevectordb/__init__.py
azure/mgmt/pineconevectordb/_client.py
azure/mgmt/pineconevectordb/_configuration.py
azure/mgmt/pineconevectordb/_model_base.py
azure/mgmt/pineconevectordb/_patch.py
azure/mgmt/pineconevectordb/_serialization.py
azure/mgmt/pineconevectordb/_version.py
azure/mgmt/pineconevectordb/py.typed
azure/mgmt/pineconevectordb/aio/__init__.py
azure/mgmt/pineconevectordb/aio/_client.py
azure/mgmt/pineconevectordb/aio/_configuration.py
azure/mgmt/pineconevectordb/aio/_patch.py
azure/mgmt/pineconevectordb/aio/operations/__init__.py
azure/mgmt/pineconevectordb/aio/operations/_operations.py
azure/mgmt/pineconevectordb/aio/operations/_patch.py
azure/mgmt/pineconevectordb/models/__init__.py
azure/mgmt/pineconevectordb/models/_enums.py
azure/mgmt/pineconevectordb/models/_models.py
azure/mgmt/pineconevectordb/models/_patch.py
azure/mgmt/pineconevectordb/operations/__init__.py
azure/mgmt/pineconevectordb/operations/_operations.py
azure/mgmt/pineconevectordb/operations/_patch.py
azure_mgmt_pineconevectordb-1.0.0b2.dist-info/LICENSE
azure_mgmt_pineconevectordb-1.0.0b2.dist-info/METADATA
azure_mgmt_pineconevectordb-1.0.0b2.dist-info/WHEEL
azure_mgmt_pineconevectordb-1.0.0b2.dist-info/top_level.txt
azure_mgmt_pineconevectordb-1.0.0b2.dist-info/RECORD
